sdram_model.v
// Simple SDRAM Model
module sdram_model (
    input         clk,
    input         reset,
    input         cs,         // Chip select
    input         ras,        // Row address strobe
    input         cas,        // Column address strobe
    input         we,         // Write enable
    input  [12:0] addr,       // Address (row or column, depending on phase)
    input  [1:0]  bank,       // Bank address
    inout  [15:0] data,       // Bidirectional data bus
    output reg    ready       // Ready flag: high when command completes
);

    // Memory array: for example, 4 banks of 16K words each (adjust as needed)
    reg [15:0] mem [0:65535];  // Simplified: 64K x 16-bit memory

    // Internal data output register; drive bus when reading.
    reg [15:0] data_out;
    assign data = (cs && !we && ready) ? data_out : 16'bz;

    // Note: This model is a simplified abstraction. A real SDRAM model
    // would include state machines to manage precharge, activate, and refresh cycles.
    always @(posedge clk) begin
        if (reset) begin
            ready <= 0;
            // Optionally, initialize memory here.
        end else begin
            // Very simple command decoding:
            // Assume that when cs is active, and both ras and cas are high,
            // a valid command is issued. If we is high, treat it as a write;
            // otherwise, as a read.
            if (cs && ras && cas) begin
                if (we) begin
                    // Write command: capture data on the bus.
                    mem[{bank, addr[12:0]}] <= data;
                    ready <= 1;
                end else begin
                    // Read command: drive the data bus with stored data.
                    data_out <= mem[{bank, addr[12:0]}];
                    ready <= 1;
                end
            end else begin
                ready <= 0;
            end
        end
    end

endmodule

sdram_controller.v
// SDRAM Controller Skeleton
module sdram_controller (
    input         clk,
    input         reset,
    // System interface signals:
    input  [15:0] write_data,     // Data to write to SDRAM
    output [15:0] read_data,      // Data read from SDRAM
    input  [21:0] address,        // Address (may include bank, row, and column info)
    input         read,           // Read enable signal
    input         write,          // Write enable signal
    output        busy,           // Controller busy flag

    // SDRAM interface signals:
    output reg    sdram_cs,       // SDRAM chip select
    output reg    sdram_ras,      // SDRAM row address strobe
    output reg    sdram_cas,      // SDRAM column address strobe
    output reg    sdram_we,       // SDRAM write enable
    output reg [12:0] sdram_addr, // SDRAM address bus
    output reg [1:0]  sdram_bank, // SDRAM bank address
    inout  [15:0] sdram_data     // Bidirectional data bus
);

    // Internal signals for state machine and data buffering
    reg [3:0] state;
    reg [15:0] data_buffer;
    
    // Example state machine states (define more as needed)
    localparam IDLE      = 4'd0,
               ACTIVATE  = 4'd1,
               READ      = 4'd2,
               WRITE     = 4'd3,
               PRECHARGE = 4'd4,
               REFRESH   = 4'd5;
               
    // State machine for SDRAM command sequencing.
    // This is only a skeleton – you will need to implement the detailed timing and command sequence.
    always @(posedge clk) begin
        if (reset) begin
            state       <= IDLE;
            sdram_cs    <= 1;
            sdram_ras   <= 1;
            sdram_cas   <= 1;
            sdram_we    <= 1;
            // Reset other control registers and buffers.
        end else begin
            case (state)
                IDLE: begin
                    // Check for read or write request.
                    // Initiate SDRAM command sequence:
                    if (read) begin
                        state <= ACTIVATE;
                        // Set up address, bank, and assert CS/RAS accordingly.
                    end else if (write) begin
                        state <= ACTIVATE;
                    end else begin
                        state <= IDLE;
                    end
                end

                ACTIVATE: begin
                    // Issue the ACTIVATE command to open a row.
                    // Transition to READ or WRITE state based on command.
                    if (read) state <= READ;
                    else if (write) state <= WRITE;
                end

                READ: begin
                    // Issue READ command: set up column address and capture data.
                    // For example: set sdram_ras, sdram_cas low, and deassert sdram_we.
                    state <= PRECHARGE;
                end

                WRITE: begin
                    // Issue WRITE command: drive sdram_data with write_data.
                    // For example: drive sdram_data and then deassert after writing.
                    state <= PRECHARGE;
                end

                PRECHARGE: begin
                    // Issue PRECHARGE command to close the row.
                    // Transition back to IDLE or REFRESH if a refresh cycle is due.
                    state <= IDLE;
                end

                REFRESH: begin
                    // Issue refresh commands periodically.
                    state <= IDLE;
                end

                default: state <= IDLE;
            endcase
        end
    end

    // Tri-state buffer for SDRAM data bus.
    // When writing, drive the bus; when reading, place the bus in high impedance.
    assign sdram_data = (state == WRITE) ? write_data : 16'bz;
    
    // Connect read_data from an internal buffer if needed.
    assign read_data = data_buffer;

    // The busy signal indicates the controller is in the midst of a transaction.
    assign busy = (state != IDLE);

endmodule

tb_sdram_controller.v
`timescale 1ns/1ps

module tb_sdram_controller;

    // Clock and reset signals
    reg         clk;
    reg         reset;

    // Memory controller interface signals
    reg  [15:0] write_data;
    wire [15:0] read_data;
    reg  [21:0] address;
    reg         read;
    reg         write;
    wire        busy;

    // SDRAM interface signals
    wire        sdram_cs;
    wire        sdram_ras;
    wire        sdram_cas;
    wire        sdram_we;
    wire [12:0] sdram_addr;
    wire [1:0]  sdram_bank;
    wire [15:0] sdram_data;

    // Instantiate the SDRAM controller
    sdram_controller uut (
        .clk(clk),
        .reset(reset),
        .write_data(write_data),
        .read_data(read_data),
        .address(address),
        .read(read),
        .write(write),
        .busy(busy),
        .sdram_cs(sdram_cs),
        .sdram_ras(sdram_ras),
        .sdram_cas(sdram_cas),
        .sdram_we(sdram_we),
        .sdram_addr(sdram_addr),
        .sdram_bank(sdram_bank),
        .sdram_data(sdram_data)
    );

    // Instantiate the SDRAM model
    sdram_model sdram_inst (
        .clk(clk),
        .reset(reset),
        .cs(sdram_cs),
        .ras(sdram_ras),
        .cas(sdram_cas),
        .we(sdram_we),
        .addr(sdram_addr),
        .bank(sdram_bank),
        .data(sdram_data),
        .ready()  // Not used here, but could be monitored if needed.
    );

    // Clock generation: 10 ns period (100 MHz clock)
    initial begin
        clk = 0;
        forever #5 clk = ~clk;
    end

    // Task to wait for busy flag to deassert with timeout checking.
    task wait_for_not_busy;
        integer timeout;
        begin
            timeout = 0;
            while (busy && timeout < 1000) begin
                #10;
                timeout = timeout + 1;
            end
            if (timeout == 1000) begin
                $display("ERROR: Timeout waiting for busy flag to deassert at time %t", $time);
                $fatal;
            end
        end
    endtask

    // Main test stimulus
    initial begin
        // Setup waveform dump for GTKWave
        $dumpfile("waveform.vcd");
        $dumpvars(0, tb_sdram_controller);

        // Initialize signals
        reset      = 1;
        write_data = 16'h0000;
        address    = 22'h0;
        read       = 0;
        write      = 0;

        // Hold reset for a few clock cycles
        #20;
        reset = 0;
        $display("INFO: Released reset at time %t", $time);

        // --- Write Operation ---
        // Write data 0xA5A5 to address 0x000001
        write_data = 16'hA5A5;
        address    = 22'h000001;
        write      = 1;
        #10;
        write      = 0;
        $display("INFO: Initiated write operation at time %t", $time);
        
        // Wait for the controller to complete the transaction
        wait_for_not_busy();
        $display("INFO: Write operation completed at time %t", $time);

        // --- Read Operation ---
        // Read from address 0x000001
        address = 22'h000001;
        read    = 1;
        #10;
        read    = 0;
        $display("INFO: Initiated read operation at time %t", $time);
        
        // Wait for the controller to complete the transaction
        wait_for_not_busy();

        // Assertion check: verify that read_data equals 0xA5A5.
        if (read_data !== 16'hA5A5) begin
            $display("ERROR: Assertion failed at time %t - expected 0xA5A5, got 0x%h", $time, read_data);
            $fatal;
        end else begin
            $display("INFO: Assertion passed at time %t - read_data equals 0xA5A5", $time);
        end

        $display("INFO: All tests completed successfully at time %t", $time);
        #50;
        $finish;
    end

endmodule

waveform.vcd
$date
	Mon Feb 24 04:15:59 2025
$end
$version
	Icarus Verilog
$end
$timescale
	1ps
$end
$scope module tb_sdram_controller $end
$var wire 16 ! sdram_data [15:0] $end
$var wire 1 " sdram_we $end
$var wire 1 # sdram_ras $end
$var wire 1 $ sdram_cs $end
$var wire 1 % sdram_cas $end
$var wire 2 & sdram_bank [1:0] $end
$var wire 13 ' sdram_addr [12:0] $end
$var wire 16 ( read_data [15:0] $end
$var wire 1 ) busy $end
$var reg 22 * address [21:0] $end
$var reg 1 + clk $end
$var reg 1 , read $end
$var reg 1 - reset $end
$var reg 1 . write $end
$var reg 16 / write_data [15:0] $end
$scope module sdram_inst $end
$var wire 1 + clk $end
$var wire 16 0 data [15:0] $end
$var wire 1 - reset $end
$var wire 1 " we $end
$var wire 1 # ras $end
$var wire 1 $ cs $end
$var wire 1 % cas $end
$var wire 2 1 bank [1:0] $end
$var wire 13 2 addr [12:0] $end
$var reg 16 3 data_out [15:0] $end
$var reg 1 4 ready $end
$upscope $end
$scope module uut $end
$var wire 22 5 address [21:0] $end
$var wire 1 + clk $end
$var wire 1 , read $end
$var wire 16 6 read_data [15:0] $end
$var wire 1 - reset $end
$var wire 16 7 sdram_data [15:0] $end
$var wire 1 . write $end
$var wire 16 8 write_data [15:0] $end
$var wire 1 ) busy $end
$var parameter 4 9 ACTIVATE $end
$var parameter 4 : IDLE $end
$var parameter 4 ; PRECHARGE $end
$var parameter 4 < READ $end
$var parameter 4 = REFRESH $end
$var parameter 4 > WRITE $end
$var reg 16 ? data_buffer [15:0] $end
$var reg 13 @ sdram_addr [12:0] $end
$var reg 2 A sdram_bank [1:0] $end
$var reg 1 % sdram_cas $end
$var reg 1 $ sdram_cs $end
$var reg 1 # sdram_ras $end
$var reg 1 " sdram_we $end
$var reg 4 B state [3:0] $end
$upscope $end
$scope task wait_for_not_busy $end
$var integer 32 C timeout [31:0] $end
$upscope $end
$upscope $end
$enddefinitions $end
$comment Show the parameter values. $end
$dumpall
b11 >
b101 =
b10 <
b100 ;
b0 :
b1 9
$end
#0
$dumpvars
bx C
bx B
bx A
bx @
bx ?
b0 8
bx 7
bx 6
b0 5
x4
bx 3
bx 2
bx 1
bx 0
b0 /
0.
1-
0,
0+
b0 *
x)
bx (
bx '
bx &
x%
x$
x#
x"
bx !
$end
#5000
bz !
bz 0
bz 7
1"
1%
1#
1$
0)
b0 B
04
1+
#10000
0+
#15000
1+
#20000
0+
1.
b1 *
b1 5
b1010010110100101 /
b1010010110100101 8
0-
#25000
1)
b1 B
14
1+
#30000
0+
b0 C
0.
#35000
1+
#40000
0+
b1 C
#45000
1+
#50000
0+
b10 C
#55000
1+
#60000
0+
b11 C
#65000
1+
#70000
0+
b100 C
#75000
1+
#80000
0+
b101 C
#85000
1+
#90000
0+
b110 C
#95000
1+
#100000
0+
b111 C
#105000
1+
#110000
0+
b1000 C
#115000
1+
#120000
0+
b1001 C
#125000
1+
#130000
0+
b1010 C
#135000
1+
#140000
0+
b1011 C
#145000
1+
#150000
0+
b1100 C
#155000
1+
#160000
0+
b1101 C
#165000
1+
#170000
0+
b1110 C
#175000
1+
#180000
0+
b1111 C
#185000
1+
#190000
0+
b10000 C
#195000
1+
#200000
0+
b10001 C
#205000
1+
#210000
0+
b10010 C
#215000
1+
#220000
0+
b10011 C
#225000
1+
#230000
0+
b10100 C
#235000
1+
#240000
0+
b10101 C
#245000
1+
#250000
0+
b10110 C
#255000
1+
#260000
0+
b10111 C
#265000
1+
#270000
0+
b11000 C
#275000
1+
#280000
0+
b11001 C
#285000
1+
#290000
0+
b11010 C
#295000
1+
#300000
0+
b11011 C
#305000
1+
#310000
0+
b11100 C
#315000
1+
#320000
0+
b11101 C
#325000
1+
#330000
0+
b11110 C
#335000
1+
#340000
0+
b11111 C
#345000
1+
#350000
0+
b100000 C
#355000
1+
#360000
0+
b100001 C
#365000
1+
#370000
0+
b100010 C
#375000
1+
#380000
0+
b100011 C
#385000
1+
#390000
0+
b100100 C
#395000
1+
#400000
0+
b100101 C
#405000
1+
#410000
0+
b100110 C
#415000
1+
#420000
0+
b100111 C
#425000
1+
#430000
0+
b101000 C
#435000
1+
#440000
0+
b101001 C
#445000
1+
#450000
0+
b101010 C
#455000
1+
#460000
0+
b101011 C
#465000
1+
#470000
0+
b101100 C
#475000
1+
#480000
0+
b101101 C
#485000
1+
#490000
0+
b101110 C
#495000
1+
#500000
0+
b101111 C
#505000
1+
#510000
0+
b110000 C
#515000
1+
#520000
0+
b110001 C
#525000
1+
#530000
0+
b110010 C
#535000
1+
#540000
0+
b110011 C
#545000
1+
#550000
0+
b110100 C
#555000
1+
#560000
0+
b110101 C
#565000
1+
#570000
0+
b110110 C
#575000
1+
#580000
0+
b110111 C
#585000
1+
#590000
0+
b111000 C
#595000
1+
#600000
0+
b111001 C
#605000
1+
#610000
0+
b111010 C
#615000
1+
#620000
0+
b111011 C
#625000
1+
#630000
0+
b111100 C
#635000
1+
#640000
0+
b111101 C
#645000
1+
#650000
0+
b111110 C
#655000
1+
#660000
0+
b111111 C
#665000
1+
#670000
0+
b1000000 C
#675000
1+
#680000
0+
b1000001 C
#685000
1+
#690000
0+
b1000010 C
#695000
1+
#700000
0+
b1000011 C
#705000
1+
#710000
0+
b1000100 C
#715000
1+
#720000
0+
b1000101 C
#725000
1+
#730000
0+
b1000110 C
#735000
1+
#740000
0+
b1000111 C
#745000
1+
#750000
0+
b1001000 C
#755000
1+
#760000
0+
b1001001 C
#765000
1+
#770000
0+
b1001010 C
#775000
1+
#780000
0+
b1001011 C
#785000
1+
#790000
0+
b1001100 C
#795000
1+
#800000
0+
b1001101 C
#805000
1+
#810000
0+
b1001110 C
#815000
1+
#820000
0+
b1001111 C
#825000
1+
#830000
0+
b1010000 C
#835000
1+
#840000
0+
b1010001 C
#845000
1+
#850000
0+
b1010010 C
#855000
1+
#860000
0+
b1010011 C
#865000
1+
#870000
0+
b1010100 C
#875000
1+
#880000
0+
b1010101 C
#885000
1+
#890000
0+
b1010110 C
#895000
1+
#900000
0+
b1010111 C
#905000
1+
#910000
0+
b1011000 C
#915000
1+
#920000
0+
b1011001 C
#925000
1+
#930000
0+
b1011010 C
#935000
1+
#940000
0+
b1011011 C
#945000
1+
#950000
0+
b1011100 C
#955000
1+
#960000
0+
b1011101 C
#965000
1+
#970000
0+
b1011110 C
#975000
1+
#980000
0+
b1011111 C
#985000
1+
#990000
0+
b1100000 C
#995000
1+
#1000000
0+
b1100001 C
#1005000
1+
#1010000
0+
b1100010 C
#1015000
1+
#1020000
0+
b1100011 C
#1025000
1+
#1030000
0+
b1100100 C
#1035000
1+
#1040000
0+
b1100101 C
#1045000
1+
#1050000
0+
b1100110 C
#1055000
1+
#1060000
0+
b1100111 C
#1065000
1+
#1070000
0+
b1101000 C
#1075000
1+
#1080000
0+
b1101001 C
#1085000
1+
#1090000
0+
b1101010 C
#1095000
1+
#1100000
0+
b1101011 C
#1105000
1+
#1110000
0+
b1101100 C
#1115000
1+
#1120000
0+
b1101101 C
#1125000
1+
#1130000
0+
b1101110 C
#1135000
1+
#1140000
0+
b1101111 C
#1145000
1+
#1150000
0+
b1110000 C
#1155000
1+
#1160000
0+
b1110001 C
#1165000
1+
#1170000
0+
b1110010 C
#1175000
1+
#1180000
0+
b1110011 C
#1185000
1+
#1190000
0+
b1110100 C
#1195000
1+
#1200000
0+
b1110101 C
#1205000
1+
#1210000
0+
b1110110 C
#1215000
1+
#1220000
0+
b1110111 C
#1225000
1+
#1230000
0+
b1111000 C
#1235000
1+
#1240000
0+
b1111001 C
#1245000
1+
#1250000
0+
b1111010 C
#1255000
1+
#1260000
0+
b1111011 C
#1265000
1+
#1270000
0+
b1111100 C
#1275000
1+
#1280000
0+
b1111101 C
#1285000
1+
#1290000
0+
b1111110 C
#1295000
1+
#1300000
0+
b1111111 C
#1305000
1+
#1310000
0+
b10000000 C
#1315000
1+
#1320000
0+
b10000001 C
#1325000
1+
#1330000
0+
b10000010 C
#1335000
1+
#1340000
0+
b10000011 C
#1345000
1+
#1350000
0+
b10000100 C
#1355000
1+
#1360000
0+
b10000101 C
#1365000
1+
#1370000
0+
b10000110 C
#1375000
1+
#1380000
0+
b10000111 C
#1385000
1+
#1390000
0+
b10001000 C
#1395000
1+
#1400000
0+
b10001001 C
#1405000
1+
#1410000
0+
b10001010 C
#1415000
1+
#1420000
0+
b10001011 C
#1425000
1+
#1430000
0+
b10001100 C
#1435000
1+
#1440000
0+
b10001101 C
#1445000
1+
#1450000
0+
b10001110 C
#1455000
1+
#1460000
0+
b10001111 C
#1465000
1+
#1470000
0+
b10010000 C
#1475000
1+
#1480000
0+
b10010001 C
#1485000
1+
#1490000
0+
b10010010 C
#1495000
1+
#1500000
0+
b10010011 C
#1505000
1+
#1510000
0+
b10010100 C
#1515000
1+
#1520000
0+
b10010101 C
#1525000
1+
#1530000
0+
b10010110 C
#1535000
1+
#1540000
0+
b10010111 C
#1545000
1+
#1550000
0+
b10011000 C
#1555000
1+
#1560000
0+
b10011001 C
#1565000
1+
#1570000
0+
b10011010 C
#1575000
1+
#1580000
0+
b10011011 C
#1585000
1+
#1590000
0+
b10011100 C
#1595000
1+
#1600000
0+
b10011101 C
#1605000
1+
#1610000
0+
b10011110 C
#1615000
1+
#1620000
0+
b10011111 C
#1625000
1+
#1630000
0+
b10100000 C
#1635000
1+
#1640000
0+
b10100001 C
#1645000
1+
#1650000
0+
b10100010 C
#1655000
1+
#1660000
0+
b10100011 C
#1665000
1+
#1670000
0+
b10100100 C
#1675000
1+
#1680000
0+
b10100101 C
#1685000
1+
#1690000
0+
b10100110 C
#1695000
1+
#1700000
0+
b10100111 C
#1705000
1+
#1710000
0+
b10101000 C
#1715000
1+
#1720000
0+
b10101001 C
#1725000
1+
#1730000
0+
b10101010 C
#1735000
1+
#1740000
0+
b10101011 C
#1745000
1+
#1750000
0+
b10101100 C
#1755000
1+
#1760000
0+
b10101101 C
#1765000
1+
#1770000
0+
b10101110 C
#1775000
1+
#1780000
0+
b10101111 C
#1785000
1+
#1790000
0+
b10110000 C
#1795000
1+
#1800000
0+
b10110001 C
#1805000
1+
#1810000
0+
b10110010 C
#1815000
1+
#1820000
0+
b10110011 C
#1825000
1+
#1830000
0+
b10110100 C
#1835000
1+
#1840000
0+
b10110101 C
#1845000
1+
#1850000
0+
b10110110 C
#1855000
1+
#1860000
0+
b10110111 C
#1865000
1+
#1870000
0+
b10111000 C
#1875000
1+
#1880000
0+
b10111001 C
#1885000
1+
#1890000
0+
b10111010 C
#1895000
1+
#1900000
0+
b10111011 C
#1905000
1+
#1910000
0+
b10111100 C
#1915000
1+
#1920000
0+
b10111101 C
#1925000
1+
#1930000
0+
b10111110 C
#1935000
1+
#1940000
0+
b10111111 C
#1945000
1+
#1950000
0+
b11000000 C
#1955000
1+
#1960000
0+
b11000001 C
#1965000
1+
#1970000
0+
b11000010 C
#1975000
1+
#1980000
0+
b11000011 C
#1985000
1+
#1990000
0+
b11000100 C
#1995000
1+
#2000000
0+
b11000101 C
#2005000
1+
#2010000
0+
b11000110 C
#2015000
1+
#2020000
0+
b11000111 C
#2025000
1+
#2030000
0+
b11001000 C
#2035000
1+
#2040000
0+
b11001001 C
#2045000
1+
#2050000
0+
b11001010 C
#2055000
1+
#2060000
0+
b11001011 C
#2065000
1+
#2070000
0+
b11001100 C
#2075000
1+
#2080000
0+
b11001101 C
#2085000
1+
#2090000
0+
b11001110 C
#2095000
1+
#2100000
0+
b11001111 C
#2105000
1+
#2110000
0+
b11010000 C
#2115000
1+
#2120000
0+
b11010001 C
#2125000
1+
#2130000
0+
b11010010 C
#2135000
1+
#2140000
0+
b11010011 C
#2145000
1+
#2150000
0+
b11010100 C
#2155000
1+
#2160000
0+
b11010101 C
#2165000
1+
#2170000
0+
b11010110 C
#2175000
1+
#2180000
0+
b11010111 C
#2185000
1+
#2190000
0+
b11011000 C
#2195000
1+
#2200000
0+
b11011001 C
#2205000
1+
#2210000
0+
b11011010 C
#2215000
1+
#2220000
0+
b11011011 C
#2225000
1+
#2230000
0+
b11011100 C
#2235000
1+
#2240000
0+
b11011101 C
#2245000
1+
#2250000
0+
b11011110 C
#2255000
1+
#2260000
0+
b11011111 C
#2265000
1+
#2270000
0+
b11100000 C
#2275000
1+
#2280000
0+
b11100001 C
#2285000
1+
#2290000
0+
b11100010 C
#2295000
1+
#2300000
0+
b11100011 C
#2305000
1+
#2310000
0+
b11100100 C
#2315000
1+
#2320000
0+
b11100101 C
#2325000
1+
#2330000
0+
b11100110 C
#2335000
1+
#2340000
0+
b11100111 C
#2345000
1+
#2350000
0+
b11101000 C
#2355000
1+
#2360000
0+
b11101001 C
#2365000
1+
#2370000
0+
b11101010 C
#2375000
1+
#2380000
0+
b11101011 C
#2385000
1+
#2390000
0+
b11101100 C
#2395000
1+
#2400000
0+
b11101101 C
#2405000
1+
#2410000
0+
b11101110 C
#2415000
1+
#2420000
0+
b11101111 C
#2425000
1+
#2430000
0+
b11110000 C
#2435000
1+
#2440000
0+
b11110001 C
#2445000
1+
#2450000
0+
b11110010 C
#2455000
1+
#2460000
0+
b11110011 C
#2465000
1+
#2470000
0+
b11110100 C
#2475000
1+
#2480000
0+
b11110101 C
#2485000
1+
#2490000
0+
b11110110 C
#2495000
1+
#2500000
0+
b11110111 C
#2505000
1+
#2510000
0+
b11111000 C
#2515000
1+
#2520000
0+
b11111001 C
#2525000
1+
#2530000
0+
b11111010 C
#2535000
1+
#2540000
0+
b11111011 C
#2545000
1+
#2550000
0+
b11111100 C
#2555000
1+
#2560000
0+
b11111101 C
#2565000
1+
#2570000
0+
b11111110 C
#2575000
1+
#2580000
0+
b11111111 C
#2585000
1+
#2590000
0+
b100000000 C
#2595000
1+
#2600000
0+
b100000001 C
#2605000
1+
#2610000
0+
b100000010 C
#2615000
1+
#2620000
0+
b100000011 C
#2625000
1+
#2630000
0+
b100000100 C
#2635000
1+
#2640000
0+
b100000101 C
#2645000
1+
#2650000
0+
b100000110 C
#2655000
1+
#2660000
0+
b100000111 C
#2665000
1+
#2670000
0+
b100001000 C
#2675000
1+
#2680000
0+
b100001001 C
#2685000
1+
#2690000
0+
b100001010 C
#2695000
1+
#2700000
0+
b100001011 C
#2705000
1+
#2710000
0+
b100001100 C
#2715000
1+
#2720000
0+
b100001101 C
#2725000
1+
#2730000
0+
b100001110 C
#2735000
1+
#2740000
0+
b100001111 C
#2745000
1+
#2750000
0+
b100010000 C
#2755000
1+
#2760000
0+
b100010001 C
#2765000
1+
#2770000
0+
b100010010 C
#2775000
1+
#2780000
0+
b100010011 C
#2785000
1+
#2790000
0+
b100010100 C
#2795000
1+
#2800000
0+
b100010101 C
#2805000
1+
#2810000
0+
b100010110 C
#2815000
1+
#2820000
0+
b100010111 C
#2825000
1+
#2830000
0+
b100011000 C
#2835000
1+
#2840000
0+
b100011001 C
#2845000
1+
#2850000
0+
b100011010 C
#2855000
1+
#2860000
0+
b100011011 C
#2865000
1+
#2870000
0+
b100011100 C
#2875000
1+
#2880000
0+
b100011101 C
#2885000
1+
#2890000
0+
b100011110 C
#2895000
1+
#2900000
0+
b100011111 C
#2905000
1+
#2910000
0+
b100100000 C
#2915000
1+
#2920000
0+
b100100001 C
#2925000
1+
#2930000
0+
b100100010 C
#2935000
1+
#2940000
0+
b100100011 C
#2945000
1+
#2950000
0+
b100100100 C
#2955000
1+
#2960000
0+
b100100101 C
#2965000
1+
#2970000
0+
b100100110 C
#2975000
1+
#2980000
0+
b100100111 C
#2985000
1+
#2990000
0+
b100101000 C
#2995000
1+
#3000000
0+
b100101001 C
#3005000
1+
#3010000
0+
b100101010 C
#3015000
1+
#3020000
0+
b100101011 C
#3025000
1+
#3030000
0+
b100101100 C
#3035000
1+
#3040000
0+
b100101101 C
#3045000
1+
#3050000
0+
b100101110 C
#3055000
1+
#3060000
0+
b100101111 C
#3065000
1+
#3070000
0+
b100110000 C
#3075000
1+
#3080000
0+
b100110001 C
#3085000
1+
#3090000
0+
b100110010 C
#3095000
1+
#3100000
0+
b100110011 C
#3105000
1+
#3110000
0+
b100110100 C
#3115000
1+
#3120000
0+
b100110101 C
#3125000
1+
#3130000
0+
b100110110 C
#3135000
1+
#3140000
0+
b100110111 C
#3145000
1+
#3150000
0+
b100111000 C
#3155000
1+
#3160000
0+
b100111001 C
#3165000
1+
#3170000
0+
b100111010 C
#3175000
1+
#3180000
0+
b100111011 C
#3185000
1+
#3190000
0+
b100111100 C
#3195000
1+
#3200000
0+
b100111101 C
#3205000
1+
#3210000
0+
b100111110 C
#3215000
1+
#3220000
0+
b100111111 C
#3225000
1+
#3230000
0+
b101000000 C
#3235000
1+
#3240000
0+
b101000001 C
#3245000
1+
#3250000
0+
b101000010 C
#3255000
1+
#3260000
0+
b101000011 C
#3265000
1+
#3270000
0+
b101000100 C
#3275000
1+
#3280000
0+
b101000101 C
#3285000
1+
#3290000
0+
b101000110 C
#3295000
1+
#3300000
0+
b101000111 C
#3305000
1+
#3310000
0+
b101001000 C
#3315000
1+
#3320000
0+
b101001001 C
#3325000
1+
#3330000
0+
b101001010 C
#3335000
1+
#3340000
0+
b101001011 C
#3345000
1+
#3350000
0+
b101001100 C
#3355000
1+
#3360000
0+
b101001101 C
#3365000
1+
#3370000
0+
b101001110 C
#3375000
1+
#3380000
0+
b101001111 C
#3385000
1+
#3390000
0+
b101010000 C
#3395000
1+
#3400000
0+
b101010001 C
#3405000
1+
#3410000
0+
b101010010 C
#3415000
1+
#3420000
0+
b101010011 C
#3425000
1+
#3430000
0+
b101010100 C
#3435000
1+
#3440000
0+
b101010101 C
#3445000
1+
#3450000
0+
b101010110 C
#3455000
1+
#3460000
0+
b101010111 C
#3465000
1+
#3470000
0+
b101011000 C
#3475000
1+
#3480000
0+
b101011001 C
#3485000
1+
#3490000
0+
b101011010 C
#3495000
1+
#3500000
0+
b101011011 C
#3505000
1+
#3510000
0+
b101011100 C
#3515000
1+
#3520000
0+
b101011101 C
#3525000
1+
#3530000
0+
b101011110 C
#3535000
1+
#3540000
0+
b101011111 C
#3545000
1+
#3550000
0+
b101100000 C
#3555000
1+
#3560000
0+
b101100001 C
#3565000
1+
#3570000
0+
b101100010 C
#3575000
1+
#3580000
0+
b101100011 C
#3585000
1+
#3590000
0+
b101100100 C
#3595000
1+
#3600000
0+
b101100101 C
#3605000
1+
#3610000
0+
b101100110 C
#3615000
1+
#3620000
0+
b101100111 C
#3625000
1+
#3630000
0+
b101101000 C
#3635000
1+
#3640000
0+
b101101001 C
#3645000
1+
#3650000
0+
b101101010 C
#3655000
1+
#3660000
0+
b101101011 C
#3665000
1+
#3670000
0+
b101101100 C
#3675000
1+
#3680000
0+
b101101101 C
#3685000
1+
#3690000
0+
b101101110 C
#3695000
1+
#3700000
0+
b101101111 C
#3705000
1+
#3710000
0+
b101110000 C
#3715000
1+
#3720000
0+
b101110001 C
#3725000
1+
#3730000
0+
b101110010 C
#3735000
1+
#3740000
0+
b101110011 C
#3745000
1+
#3750000
0+
b101110100 C
#3755000
1+
#3760000
0+
b101110101 C
#3765000
1+
#3770000
0+
b101110110 C
#3775000
1+
#3780000
0+
b101110111 C
#3785000
1+
#3790000
0+
b101111000 C
#3795000
1+
#3800000
0+
b101111001 C
#3805000
1+
#3810000
0+
b101111010 C
#3815000
1+
#3820000
0+
b101111011 C
#3825000
1+
#3830000
0+
b101111100 C
#3835000
1+
#3840000
0+
b101111101 C
#3845000
1+
#3850000
0+
b101111110 C
#3855000
1+
#3860000
0+
b101111111 C
#3865000
1+
#3870000
0+
b110000000 C
#3875000
1+
#3880000
0+
b110000001 C
#3885000
1+
#3890000
0+
b110000010 C
#3895000
1+
#3900000
0+
b110000011 C
#3905000
1+
#3910000
0+
b110000100 C
#3915000
1+
#3920000
0+
b110000101 C
#3925000
1+
#3930000
0+
b110000110 C
#3935000
1+
#3940000
0+
b110000111 C
#3945000
1+
#3950000
0+
b110001000 C
#3955000
1+
#3960000
0+
b110001001 C
#3965000
1+
#3970000
0+
b110001010 C
#3975000
1+
#3980000
0+
b110001011 C
#3985000
1+
#3990000
0+
b110001100 C
#3995000
1+
#4000000
0+
b110001101 C
#4005000
1+
#4010000
0+
b110001110 C
#4015000
1+
#4020000
0+
b110001111 C
#4025000
1+
#4030000
0+
b110010000 C
#4035000
1+
#4040000
0+
b110010001 C
#4045000
1+
#4050000
0+
b110010010 C
#4055000
1+
#4060000
0+
b110010011 C
#4065000
1+
#4070000
0+
b110010100 C
#4075000
1+
#4080000
0+
b110010101 C
#4085000
1+
#4090000
0+
b110010110 C
#4095000
1+
#4100000
0+
b110010111 C
#4105000
1+
#4110000
0+
b110011000 C
#4115000
1+
#4120000
0+
b110011001 C
#4125000
1+
#4130000
0+
b110011010 C
#4135000
1+
#4140000
0+
b110011011 C
#4145000
1+
#4150000
0+
b110011100 C
#4155000
1+
#4160000
0+
b110011101 C
#4165000
1+
#4170000
0+
b110011110 C
#4175000
1+
#4180000
0+
b110011111 C
#4185000
1+
#4190000
0+
b110100000 C
#4195000
1+
#4200000
0+
b110100001 C
#4205000
1+
#4210000
0+
b110100010 C
#4215000
1+
#4220000
0+
b110100011 C
#4225000
1+
#4230000
0+
b110100100 C
#4235000
1+
#4240000
0+
b110100101 C
#4245000
1+
#4250000
0+
b110100110 C
#4255000
1+
#4260000
0+
b110100111 C
#4265000
1+
#4270000
0+
b110101000 C
#4275000
1+
#4280000
0+
b110101001 C
#4285000
1+
#4290000
0+
b110101010 C
#4295000
1+
#4300000
0+
b110101011 C
#4305000
1+
#4310000
0+
b110101100 C
#4315000
1+
#4320000
0+
b110101101 C
#4325000
1+
#4330000
0+
b110101110 C
#4335000
1+
#4340000
0+
b110101111 C
#4345000
1+
#4350000
0+
b110110000 C
#4355000
1+
#4360000
0+
b110110001 C
#4365000
1+
#4370000
0+
b110110010 C
#4375000
1+
#4380000
0+
b110110011 C
#4385000
1+
#4390000
0+
b110110100 C
#4395000
1+
#4400000
0+
b110110101 C
#4405000
1+
#4410000
0+
b110110110 C
#4415000
1+
#4420000
0+
b110110111 C
#4425000
1+
#4430000
0+
b110111000 C
#4435000
1+
#4440000
0+
b110111001 C
#4445000
1+
#4450000
0+
b110111010 C
#4455000
1+
#4460000
0+
b110111011 C
#4465000
1+
#4470000
0+
b110111100 C
#4475000
1+
#4480000
0+
b110111101 C
#4485000
1+
#4490000
0+
b110111110 C
#4495000
1+
#4500000
0+
b110111111 C
#4505000
1+
#4510000
0+
b111000000 C
#4515000
1+
#4520000
0+
b111000001 C
#4525000
1+
#4530000
0+
b111000010 C
#4535000
1+
#4540000
0+
b111000011 C
#4545000
1+
#4550000
0+
b111000100 C
#4555000
1+
#4560000
0+
b111000101 C
#4565000
1+
#4570000
0+
b111000110 C
#4575000
1+
#4580000
0+
b111000111 C
#4585000
1+
